xlassify/__init__.py
xlassify/interface.py
xlassify/interface_test.py
xlassify/dataset/__init__.py
xlassify/dataset/genus_full.csv
xlassify/dataset/genus_partial.csv
xlassify/dataset/species_full.csv
xlassify/dataset/species_label_df.csv
xlassify/dataset/species_partial.csv
xlassify/dataset/test/test.fasta
xlassify/model/__init__.py
xlassify/model/ge5_le50_f5_m7_res_0_drop_seed0_f4_last.ckpt
xlassify/network/__init__.py
xlassify/network/model.py
xlassify/tools/__init__.py
xlassify/tools/kmer_utils.py
Xlassify-1.0.0.dist-info/LICENSE
Xlassify-1.0.0.dist-info/METADATA
Xlassify-1.0.0.dist-info/WHEEL
Xlassify-1.0.0.dist-info/entry_points.txt
Xlassify-1.0.0.dist-info/top_level.txt
Xlassify-1.0.0.dist-info/RECORD
