Metadata-Version: 2.1
Name: Xlassify
Version: 1.0.0
Summary: An alignment-free deep-learning model trained to classify human gut bacteria
Home-page: https://github.com/SenseTime-Knowledge-Mining/Xlassify
Author: kangkun
Author-email: maokangkun@pjlab.org.cn
License: UNKNOWN
Project-URL: Bug Tracker, https://github.com/SenseTime-Knowledge-Mining/Xlassify/issues
Keywords: Xlassify,genome,microbiome,taxonomic,bacteria
Platform: any
Classifier: Programming Language :: Python :: 3
Classifier: License :: OSI Approved :: MIT License
Classifier: Operating System :: OS Independent
Requires-Python: >=3.7.1
License-File: LICENSE
Requires-Dist: numpy (>=1.18)
Requires-Dist: pandas (>=1.1)
Requires-Dist: torch (>=1.7)
Requires-Dist: tqdm
Requires-Dist: requests
